surface_scenarios-0.2.0.dist-info/licenses/LICENSE
survi_scenarios/__init__.py
survi_scenarios/geom.py
survi_scenarios/loaders.py
survi_scenarios/rng.py
survi_scenarios/suite.py
survi_scenarios/synthetic.py
survi_scenarios/synthetic_3d.py
survi_scenarios/types.py
survi_scenarios/units.py
survi_scenarios/data/scenarios/alpine_ridge_long.json
survi_scenarios/data/scenarios/bumpy_heterogeneous.json
survi_scenarios/data/scenarios/compact_extreme_relief.json
survi_scenarios/data/scenarios/complex_random_polygon.json
survi_scenarios/data/scenarios/flat_rect_small.json
survi_scenarios/data/scenarios/lshape_rippled.json
survi_scenarios/data/scenarios/mountainous_600x400.json
survi_scenarios/data/scenarios/ripples_two_angles.json
survi_scenarios/data/scenarios/sloped_rotated_rect.json
survi_scenarios/data/scenarios/small_steep_micro.json
survi_scenarios/data/scenarios/suite_manifest.json
survi_scenarios/data/scenarios/tiny_crater.json
survi_scenarios/data/scenarios/vif_structured_residual.json
survi_scenarios/data/scenarios/trenchfoot/SUMMARY.json
survi_scenarios/data/scenarios/trenchfoot/S01_straight_vwalls/metrics.json
survi_scenarios/data/scenarios/trenchfoot/S01_straight_vwalls/preview.png
survi_scenarios/data/scenarios/trenchfoot/S01_straight_vwalls/preview_oblique.png
survi_scenarios/data/scenarios/trenchfoot/S01_straight_vwalls/preview_side.png
survi_scenarios/data/scenarios/trenchfoot/S01_straight_vwalls/preview_top.png
survi_scenarios/data/scenarios/trenchfoot/S01_straight_vwalls/scene.json
survi_scenarios/data/scenarios/trenchfoot/S01_straight_vwalls/trench_scene.obj
survi_scenarios/data/scenarios/trenchfoot/S01_straight_vwalls/meshes/trench_scene_culled.obj
survi_scenarios/data/scenarios/trenchfoot/S01_straight_vwalls/point_clouds/culled/resolution0p050.las
survi_scenarios/data/scenarios/trenchfoot/S01_straight_vwalls/point_clouds/full/resolution0p050.las
survi_scenarios/data/scenarios/trenchfoot/S02_straight_slope_pipe/metrics.json
survi_scenarios/data/scenarios/trenchfoot/S02_straight_slope_pipe/preview.png
surface_scenarios-0.2.0.dist-info/METADATA
surface_scenarios-0.2.0.dist-info/WHEEL
surface_scenarios-0.2.0.dist-info/top_level.txt
surface_scenarios-0.2.0.dist-info/RECORD
