Metadata-Version: 2.4
Name: surface-scenarios
Version: 0.2.0
Summary: Standalone synthetic elevation and SDF scenario library extracted from Survi
Author: Survi Team
License: Apache-2.0
Project-URL: Homepage, https://example.com/survi-scenarios
Project-URL: Source, https://example.com/survi-scenarios
Classifier: License :: OSI Approved :: Apache Software License
Classifier: Programming Language :: Python
Classifier: Programming Language :: Python :: 3
Classifier: Programming Language :: Python :: 3.10
Classifier: Programming Language :: Python :: 3.11
Classifier: Programming Language :: Python :: 3.12
Classifier: Intended Audience :: Developers
Classifier: Topic :: Scientific/Engineering
Requires-Python: >=3.10
License-File: LICENSE
Requires-Dist: numpy>=1.24
Requires-Dist: pandas>=2.1
Requires-Dist: shapely>=2.0
Provides-Extra: mesh
Requires-Dist: trimesh>=4.0; extra == "mesh"
Dynamic: license-file
